LICENSE
MANIFEST.in
NEWS
README.rst
setup.cfg
setup.py
Pythonect.egg-info/PKG-INFO
Pythonect.egg-info/SOURCES.txt
Pythonect.egg-info/dependency_links.txt
Pythonect.egg-info/not-zip-safe
Pythonect.egg-info/requires.txt
Pythonect.egg-info/top_level.txt
bin/__init__.py
bin/_preamble.py
bin/pythonect
doc/Makefile
doc/api.rst
doc/changelog.rst
doc/conf.py
doc/foreword.rst
doc/index.rst
doc/installation.rst
doc/license.rst
doc/make.bat
doc/requirements.txt
doc/_static/123_sum_reduce.png
doc/_static/123_to_print.png
doc/_static/dia_step_0.jpeg
doc/_static/dia_step_0.png
doc/_static/dia_step_1.png
doc/_static/dia_step_2.png
doc/_static/dia_step_3.png
doc/_static/dia_step_4.png
doc/_static/dia_step_5.png
doc/_static/dia_step_6.png
doc/_static/dia_step_7.png
doc/_static/dia_step_8.png
doc/_static/helloworld_1_2.png
doc/_static/multiple_x_values.png
doc/_static/single_x_value.png
doc/_templates/page.html
doc/tutorial/controlflow.rst
doc/tutorial/flow.rst
doc/tutorial/helloworld.rst
doc/tutorial/index.rst
doc/tutorial/interpreter.rst
doc/tutorial/power.rst
doc/tutorial/vars.rst
examples/hello.dia
examples/hello.p2y
examples/palindrome.dia
examples/repl.dia
pythonect/__init__.py
pythonect/_version.py
pythonect/internal/__init__.py
pythonect/internal/_graph.py
pythonect/internal/_ordereddict.py
pythonect/internal/eval.py
pythonect/internal/lang.py
pythonect/internal/version.py
pythonect/internal/parsers/__init__.py
pythonect/internal/parsers/dia.py
pythonect/internal/parsers/p2y.py
pythonect/internal/parsers/vdx.py
pythonect/internal/parsers/test/__init__.py
pythonect/internal/parsers/test/test_dia.py
pythonect/internal/parsers/test/test_p2y.py
pythonect/internal/parsers/test/test_vdx07.py
pythonect/internal/parsers/test/test_vdx10.py
pythonect/test/__init__.py
pythonect/test/eval_tst_gen.py
pythonect/test/test_eval.py
pythonect/test/test_xmlrpc_app.py