Metadata-Version: 1.1
Name: Pythonect
Version: 0.6.0
Summary: A general-purpose dataflow programming language based on Python, written in Python
Home-page: http://www.pythonect.org/
Author: Itzik Kotler
Author-email: xorninja@gmail.com
License: BSD
Platform: UNKNOWN
Classifier: Development Status :: 4 - Beta
Classifier: License :: OSI Approved :: BSD License
Classifier: Operating System :: OS Independent
Classifier: Programming Language :: Python
Classifier: Programming Language :: Python :: 2.7
Classifier: Programming Language :: Python :: 2.6
